Metadata-Version: 2.1
Name: basic-task-manager
Version: 1.0.0
Summary: A task manager application
Home-page: UNKNOWN
Author: GautamSagarMallela
License: UNKNOWN
Platform: UNKNOWN
